dscitools/__init__.py
dscitools/common.py
dscitools/general.py
dscitools/ipython.py
dscitools/pandas.py
dscitools/spark.py
other/__init__.py
other/other.py
other/old_tests/__init__.py
other/old_tests/_test_ggplot_tools.py
other/old_tests/t.py
dscitools-0.1.2.dist-info/METADATA
dscitools-0.1.2.dist-info/WHEEL
dscitools-0.1.2.dist-info/top_level.txt
dscitools-0.1.2.dist-info/RECORD
